hypothtst/__init__.py
hypothtst/alpha_beta_sim.py
hypothtst/hypoth_tst_simulator.py
hypothtst/neg_binom_tst.py
hypothtst/fn_utils/__init__.py
hypothtst/fn_utils/rate/__init__.py
hypothtst/fn_utils/rate/beta_to_t.py
hypothtst/sim_utils/__init__.py
hypothtst/sim_utils/mean/__init__.py
hypothtst/sim_utils/mean/normal.py
hypothtst/sim_utils/rate/__init__.py
hypothtst/sim_utils/rate/poisson.py
hypothtst/tst/__init__.py
hypothtst/tst/correlation/__init__.py
hypothtst/tst/correlation/pt_processes.py
hypothtst/tst/stochparams/__init__.py
hypothtst/tst/stochparams/mean/__init__.py
hypothtst/tst/stochparams/mean/t_test.py
hypothtst/tst/stochparams/mean/t_test_sim.py
hypothtst/tst/stochparams/p_heads/__init__.py
hypothtst/tst/stochparams/p_heads/binom_test.py
hypothtst/tst/stochparams/percentiles/__init__.py
hypothtst/tst/stochparams/percentiles/tst_percentiles.py
hypothtst/tst/stochparams/rate/__init__.py
hypothtst/tst/stochparams/rate/diff.py
hypothtst/tst/stochparams/rate/time_binned.py
hypothtst/tst/stochparams/rate/ump.py
hypothtst/viz_utils/__init__.py
hypothtst/viz_utils/plots_on_pvals.py
hypothtst-0.0.12.dist-info/METADATA
hypothtst-0.0.12.dist-info/WHEEL
hypothtst-0.0.12.dist-info/top_level.txt
hypothtst-0.0.12.dist-info/RECORD
