Metadata-Version: 2.1
Name: hypothtst
Version: 0.0.12
Summary: Add static script_dir() method to Path
Home-page: https://github.com/ryu577/hypothtst
Author: Rohit Pandey
Author-email: rohitpandey576@gmail.com
License: MIT
Platform: UNKNOWN
